README.rst
setup.py
uxadt/__init__.py
uxadt/uxadt.py
uxadt.egg-info/PKG-INFO
uxadt.egg-info/SOURCES.txt
uxadt.egg-info/dependency_links.txt
uxadt.egg-info/top_level.txt