Metadata-Version: 1.0
Name: uxadt
Version: 0.1.0.0
Summary: Cross-platform embedded representation for algebraic data types, values, and common operations.
Home-page: http://uxadt.org
Author: Andrei Lapets
Author-email: a@lapets.io
License: MIT
Platform: UNKNOWN
